rsoccer_gym/__init__.py
rsoccer_gym/Entities/Ball.py
rsoccer_gym/Entities/Field.py
rsoccer_gym/Entities/Frame.py
rsoccer_gym/Entities/Robot.py
rsoccer_gym/Entities/__init__.py
rsoccer_gym/Render/Render.py
rsoccer_gym/Render/__init__.py
rsoccer_gym/Simulators/__init__.py
rsoccer_gym/Simulators/fira.py
rsoccer_gym/Simulators/rsim.py
rsoccer_gym/Simulators/pb_fira/__init__.py
rsoccer_gym/Simulators/pb_fira/command_fira_pb2.py
rsoccer_gym/Simulators/pb_fira/command_pb2.py
rsoccer_gym/Simulators/pb_fira/common_pb2.py
rsoccer_gym/Simulators/pb_fira/packet_pb2.py
rsoccer_gym/Simulators/pb_fira/replacement_pb2.py
rsoccer_gym/Simulators/pb_fira/state_pb2.py
rsoccer_gym/Utils/Utils.py
rsoccer_gym/Utils/__init__.py
rsoccer_gym/Utils/kdtree.py
rsoccer_gym/Utils/kdtree_test.py
rsoccer_gym/ssl/__init__.py
rsoccer_gym/ssl/ssl_gym_base.py
rsoccer_gym/ssl/ssl_go_to_ball/__init__.py
rsoccer_gym/ssl/ssl_go_to_ball/ssl_gym_go_to_ball.py
rsoccer_gym/ssl/ssl_go_to_ball/ssl_gym_go_to_ball_ir.py
rsoccer_gym/ssl/ssl_go_to_ball_shoot/__init__.py
rsoccer_gym/ssl/ssl_go_to_ball_shoot/ssl_gym_go_to_ball_shoot.py
rsoccer_gym/ssl/ssl_hw_challenge/__init__.py
rsoccer_gym/ssl/ssl_hw_challenge/contested_possession.py
rsoccer_gym/ssl/ssl_hw_challenge/dribbling.py
rsoccer_gym/ssl/ssl_hw_challenge/pass_endurance.py
rsoccer_gym/ssl/ssl_hw_challenge/pass_endurance_ma.py
rsoccer_gym/ssl/ssl_hw_challenge/static_defenders.py
rsoccer_gym/vss/__init__.py
rsoccer_gym/vss/vss_gym_base.py
rsoccer_gym/vss/env_gk/__init__.py
rsoccer_gym/vss/env_gk/vss_gk.py
rsoccer_gym/vss/env_ma/__init__.py
rsoccer_gym/vss/env_ma/vss_gym_ma.py
rsoccer_gym/vss/env_vss/__init__.py
rsoccer_gym/vss/env_vss/vss_gym.py
rsoccer_gym/vss/env_vss/vss_gym_fira.py
rsoccer_gym-1.4.dist-info/METADATA
rsoccer_gym-1.4.dist-info/WHEEL
rsoccer_gym-1.4.dist-info/top_level.txt
rsoccer_gym-1.4.dist-info/RECORD
