Metadata-Version: 2.1
Name: rsoccer-gym
Version: 1.4
Summary: SSL and VSS robot soccer gym environments
Home-page: https://github.com/robocin/rSoccer
License: UNKNOWN
Platform: UNKNOWN
Requires-Dist: gym
Requires-Dist: rc-robosim (>=1.2.0)
Requires-Dist: pyglet
Requires-Dist: protobuf
